fedland/database_models/client_stat.py
fedland/database_models/experiment.py
fedland/loaders.py
fedland/metrics/__init__.py
fedland/metrics/frobenius.py
fedland/metrics/pac_bayes.py
fedland/metrics/path_norm.py
fedland/networks.py
fedland-0.3.0.dist-info/METADATA
fedland-0.3.0.dist-info/WHEEL
fedland-0.3.0.dist-info/RECORD
