Metadata-Version: 2.1
Name: fedland
Version: 0.3.0
Summary: Research Libary for Federated Learing Loss Landscapes
License: None
Author: Finn Vaughankraska
Requires-Python: >=3.11,<3.12
Classifier: License :: Other/Proprietary License
Classifier: Programming Language :: Python :: 3
Classifier: Programming Language :: Python :: 3.11
Requires-Dist: fedn (>=0.16.1,<0.17.0)
Requires-Dist: numpy (>=2.1.2)
Requires-Dist: python-dotenv (>=1.0.1,<2.0.0)
Requires-Dist: scipy (>=1.14.1,<2.0.0)
Requires-Dist: torch (>=2.4.1,<3.0.0)
Requires-Dist: torchaudio (>=2.4.1,<3.0.0)
Requires-Dist: torchvision (>=0.19.1,<0.20.0)
